[{"id":"33633547921","name":"Retrospect Labs Pty Ltd","abn":"33633547921","buyictURL":"https://www.buyict.gov.au/public?id=seller_details&abn=33633547921","panels":[{"panelName":"Digital Marketplace Panel 2","panelId":"DMP2","category":"ICT Services","jurisdiction":"Federal","deedStart":"01-Jul-2023","deedEnd":"30-Jun-2028","isActive":true}]},{"id":"87616642696","name":"Revenite Pty Ltd","abn":"87616642696","buyictURL":"https://www.buyict.gov.au/public?id=seller_details&abn=87616642696","panels":[{"panelName":"Digital Marketplace Panel 2","panelId":"DMP2","category":"ICT Services","jurisdiction":"Federal","deedStart":"01-Jul-2023","deedEnd":"30-Jun-2028","isActive":true}]},{"id":"75520781416","name":"Revium Pty Ltd","abn":"75520781416","buyictURL":"https://www.buyict.gov.au/public?id=seller_details&abn=75520781416","panels":[{"panelName":"Digital Marketplace Panel 2","panelId":"DMP2","category":"ICT Services","jurisdiction":"Federal","deedStart":"01-Jul-2023","deedEnd":"30-Jun-2028","isActive":true}]},{"id":"23650331427","name":"Rhodium Solutions","abn":"23650331427","buyictURL":"https://www.buyict.gov.au/public?id=seller_details&abn=23650331427","panels":[{"panelName":"Digital Marketplace Panel 2","panelId":"DMP2","category":"ICT Services","jurisdiction":"Federal","deedStart":"01-Jul-2023","deedEnd":"30-Jun-2028","isActive":true}]},{"id":"30000593171","name":"Ricoh Australia Pty Ltd","abn":"30000593171","buyictURL":"https://www.buyict.gov.au/public?id=seller_details&abn=30000593171","headquarters":"NSW1640","panels":[{"panelName":"Hardware Marketplace","panelId":"PNL1868","category":"Hardware","jurisdiction":"Federal","deedStart":"24-Sep-2018","deedEnd":"30-Jun-2026","isActive":true}]},{"id":"96680373979","name":"RIGEL SOLUTIONS PTY LTD","abn":"96680373979","buyictURL":"https://www.buyict.gov.au/public?id=seller_details&abn=96680373979","panels":[{"panelName":"Digital Marketplace Panel 2","panelId":"DMP2","category":"ICT Services","jurisdiction":"Federal","deedStart":"01-Jul-2023","deedEnd":"30-Jun-2028","isActive":true}]},{"id":"47642041110","name":"RISK ADAPTED SERVICES PTY LTD","abn":"47642041110","buyictURL":"https://www.buyict.gov.au/public?id=seller_details&abn=47642041110","panels":[{"panelName":"Digital Marketplace Panel 2","panelId":"DMP2","category":"ICT Services","jurisdiction":"Federal","deedStart":"01-Jul-2023","deedEnd":"30-Jun-2028","isActive":true}]},{"id":"51164006902","name":"Riskstream","abn":"51164006902","buyictURL":"https://www.buyict.gov.au/public?id=seller_details&abn=51164006902","panels":[{"panelName":"Digital Marketplace Panel 2","panelId":"DMP2","category":"ICT Services","jurisdiction":"Federal","deedStart":"01-Jul-2023","deedEnd":"30-Jun-2028","isActive":true}]},{"id":"94092040018","name":"RKM Consulting","abn":"94092040018","buyictURL":"https://www.buyict.gov.au/public?id=seller_details&abn=94092040018","panels":[{"panelName":"Digital Marketplace Panel 2","panelId":"DMP2","category":"ICT Services","jurisdiction":"Federal","deedStart":"01-Jul-2023","deedEnd":"30-Jun-2028","isActive":true}]},{"id":"41122477614","name":"Roaming Technologies Pty Ltd","abn":"41122477614","buyictURL":"https://www.buyict.gov.au/public?id=seller_details&abn=41122477614","headquarters":"WA6104","panels":[{"panelName":"Hardware Marketplace","panelId":"PNL1868","category":"Hardware","jurisdiction":"Federal","deedStart":"24-Sep-2018","deedEnd":"30-Jun-2026","isActive":true}]},{"id":"14082197840","name":"Rob Dobson & Associates","abn":"14082197840","buyictURL":"https://www.buyict.gov.au/public?id=seller_details&abn=14082197840","panels":[{"panelName":"Digital Marketplace Panel 2","panelId":"DMP2","category":"ICT Services","jurisdiction":"Federal","deedStart":"01-Jul-2023","deedEnd":"30-Jun-2028","isActive":true}]},{"id":"62126118269","name":"Robinson Ryan Pty Ltd","abn":"62126118269","buyictURL":"https://www.buyict.gov.au/public?id=seller_details&abn=62126118269","panels":[{"panelName":"Digital Marketplace Panel 2","panelId":"DMP2","category":"ICT Services","jurisdiction":"Federal","deedStart":"01-Jul-2023","deedEnd":"30-Jun-2028","isActive":true}]},{"id":"66656663919","name":"Robust Policy","abn":"66656663919","buyictURL":"https://www.buyict.gov.au/public?id=seller_details&abn=66656663919","panels":[{"panelName":"Digital Marketplace Panel 2","panelId":"DMP2","category":"ICT Services","jurisdiction":"Federal","deedStart":"01-Jul-2023","deedEnd":"30-Jun-2028","isActive":true}]},{"id":"73153698036","name":"Roll Inn Pty Ltd","abn":"73153698036","buyictURL":"https://www.buyict.gov.au/public?id=seller_details&abn=73153698036","panels":[{"panelName":"Digital Marketplace Panel 2","panelId":"DMP2","category":"ICT Services","jurisdiction":"Federal","deedStart":"01-Jul-2023","deedEnd":"30-Jun-2028","isActive":true}]},{"id":"14644563468","name":"Rosella Street","abn":"14644563468","buyictURL":"https://www.buyict.gov.au/public?id=seller_details&abn=14644563468","panels":[{"panelName":"Digital Marketplace Panel 2","panelId":"DMP2","category":"ICT Services","jurisdiction":"Federal","deedStart":"01-Jul-2023","deedEnd":"30-Jun-2028","isActive":true}]},{"id":"12158255648","name":"Rowdy Inc","abn":"12158255648","buyictURL":"https://www.buyict.gov.au/public?id=seller_details&abn=12158255648","panels":[{"panelName":"Digital Marketplace Panel 2","panelId":"DMP2","category":"ICT Services","jurisdiction":"Federal","deedStart":"01-Jul-2023","deedEnd":"30-Jun-2028","isActive":true}]},{"id":"44628921693","name":"RoZetta Technology","abn":"44628921693","buyictURL":"https://www.buyict.gov.au/public?id=seller_details&abn=44628921693","panels":[{"panelName":"Digital Marketplace Panel 2","panelId":"DMP2","category":"ICT Services","jurisdiction":"Federal","deedStart":"01-Jul-2023","deedEnd":"30-Jun-2028","isActive":true}]},{"id":"67087759171","name":"RP Data Pty Ltd t/a Cotality","abn":"67087759171","buyictURL":"https://www.buyict.gov.au/public?id=seller_details&abn=67087759171","panels":[{"panelName":"Digital Marketplace Panel 2","panelId":"DMP2","category":"ICT Services","jurisdiction":"Federal","deedStart":"01-Jul-2023","deedEnd":"30-Jun-2028","isActive":true}]},{"id":"97117432354","name":"RPV Consultants","abn":"97117432354","buyictURL":"https://www.buyict.gov.au/public?id=seller_details&abn=97117432354","panels":[{"panelName":"Digital Marketplace Panel 2","panelId":"DMP2","category":"ICT Services","jurisdiction":"Federal","deedStart":"01-Jul-2023","deedEnd":"30-Jun-2028","isActive":true}]},{"id":"65319382479","name":"RSM Australia","abn":"65319382479","buyictURL":"https://www.buyict.gov.au/public?id=seller_details&abn=65319382479","panels":[{"panelName":"Digital Marketplace Panel 2","panelId":"DMP2","category":"ICT Services","jurisdiction":"Federal","deedStart":"01-Jul-2023","deedEnd":"30-Jun-2028","isActive":true}]},{"id":"56653968901","name":"RTEM SERVICES","abn":"56653968901","buyictURL":"https://www.buyict.gov.au/public?id=seller_details&abn=56653968901","panels":[{"panelName":"Digital Marketplace Panel 2","panelId":"DMP2","category":"ICT Services","jurisdiction":"Federal","deedStart":"01-Jul-2023","deedEnd":"30-Jun-2028","isActive":true}]},{"id":"89608877630","name":"Ruatec","abn":"89608877630","buyictURL":"https://www.buyict.gov.au/public?id=seller_details&abn=89608877630","panels":[{"panelName":"Digital Marketplace Panel 2","panelId":"DMP2","category":"ICT Services","jurisdiction":"Federal","deedStart":"01-Jul-2023","deedEnd":"30-Jun-2028","isActive":true}]},{"id":"99167081772","name":"Rubix Solutions Pty Ltd","abn":"99167081772","buyictURL":"https://www.buyict.gov.au/public?id=seller_details&abn=99167081772","panels":[{"panelName":"Digital Marketplace Panel 2","panelId":"DMP2","category":"ICT Services","jurisdiction":"Federal","deedStart":"01-Jul-2023","deedEnd":"30-Jun-2028","isActive":true}]},{"id":"38604321048","name":"S & I SOLUTIONS PTY. LTD.","abn":"38604321048","buyictURL":"https://www.buyict.gov.au/public?id=seller_details&abn=38604321048","panels":[{"panelName":"Digital Marketplace Panel 2","panelId":"DMP2","category":"ICT Services","jurisdiction":"Federal","deedStart":"01-Jul-2023","deedEnd":"30-Jun-2028","isActive":true}]},{"id":"84637770739","name":"S&IG","abn":"84637770739","buyictURL":"https://www.buyict.gov.au/public?id=seller_details&abn=84637770739","panels":[{"panelName":"Digital Marketplace Panel 2","panelId":"DMP2","category":"ICT Services","jurisdiction":"Federal","deedStart":"01-Jul-2023","deedEnd":"30-Jun-2028","isActive":true}]},{"id":"39649700158","name":"S&K TECHNOLOGIES PTY LTD","abn":"39649700158","buyictURL":"https://www.buyict.gov.au/public?id=seller_details&abn=39649700158","panels":[{"panelName":"Digital Marketplace Panel 2","panelId":"DMP2","category":"ICT Services","jurisdiction":"Federal","deedStart":"01-Jul-2023","deedEnd":"30-Jun-2028","isActive":true}]},{"id":"88008643212","name":"Saab Australia Pty Ltd","abn":"88008643212","buyictURL":"https://www.buyict.gov.au/public?id=seller_details&abn=88008643212","panels":[{"panelName":"Digital Marketplace Panel 2","panelId":"DMP2","category":"ICT Services","jurisdiction":"Federal","deedStart":"01-Jul-2023","deedEnd":"30-Jun-2028","isActive":true}]},{"id":"48098914848","name":"SAFETRAC PTY LIMITED","abn":"48098914848","buyictURL":"https://www.buyict.gov.au/public?id=seller_details&abn=48098914848","panels":[{"panelName":"Digital Marketplace Panel 2","panelId":"DMP2","category":"ICT Services","jurisdiction":"Federal","deedStart":"01-Jul-2023","deedEnd":"30-Jun-2028","isActive":true}]},{"id":"65601557082","name":"Sage Energy Systems","abn":"65601557082","buyictURL":"https://www.buyict.gov.au/public?id=seller_details&abn=65601557082","panels":[{"panelName":"Digital Marketplace Panel 2","panelId":"DMP2","category":"ICT Services","jurisdiction":"Federal","deedStart":"01-Jul-2023","deedEnd":"30-Jun-2028","isActive":true}]},{"id":"87606806866","name":"SAHASRA IT PTY LTD","abn":"87606806866","buyictURL":"https://www.buyict.gov.au/public?id=seller_details&abn=87606806866","panels":[{"panelName":"Digital Marketplace Panel 2","panelId":"DMP2","category":"ICT Services","jurisdiction":"Federal","deedStart":"01-Jul-2023","deedEnd":"30-Jun-2028","isActive":true}]},{"id":"37636480512","name":"SAHR Professional Services","abn":"37636480512","buyictURL":"https://www.buyict.gov.au/public?id=seller_details&abn=37636480512","panels":[{"panelName":"Digital Marketplace Panel 2","panelId":"DMP2","category":"ICT Services","jurisdiction":"Federal","deedStart":"01-Jul-2023","deedEnd":"30-Jun-2028","isActive":true}]},{"id":"29660549253","name":"SAJJ CONSULTING PTY LTD","abn":"29660549253","buyictURL":"https://www.buyict.gov.au/public?id=seller_details&abn=29660549253","panels":[{"panelName":"Digital Marketplace Panel 2","panelId":"DMP2","category":"ICT Services","jurisdiction":"Federal","deedStart":"01-Jul-2023","deedEnd":"30-Jun-2028","isActive":true}]},{"id":"86663717851","name":"Salorix","abn":"86663717851","buyictURL":"https://www.buyict.gov.au/public?id=seller_details&abn=86663717851","panels":[{"panelName":"Digital Marketplace Panel 2","panelId":"DMP2","category":"ICT Services","jurisdiction":"Federal","deedStart":"01-Jul-2023","deedEnd":"30-Jun-2028","isActive":true}]},{"id":"85676742328","name":"Salsa Digital","abn":"85676742328","buyictURL":"https://www.buyict.gov.au/public?id=seller_details&abn=85676742328","panels":[{"panelName":"Digital Marketplace Panel 2","panelId":"DMP2","category":"ICT Services","jurisdiction":"Federal","deedStart":"01-Jul-2023","deedEnd":"30-Jun-2028","isActive":true}]},{"id":"21601492095","name":"Saltworth Pty Ltd","abn":"21601492095","buyictURL":"https://www.buyict.gov.au/public?id=seller_details&abn=21601492095","panels":[{"panelName":"Digital Marketplace Panel 2","panelId":"DMP2","category":"ICT Services","jurisdiction":"Federal","deedStart":"01-Jul-2023","deedEnd":"30-Jun-2028","isActive":true}]},{"id":"64609768587","name":"Salutem Consulting","abn":"64609768587","buyictURL":"https://www.buyict.gov.au/public?id=seller_details&abn=64609768587","panels":[{"panelName":"Digital Marketplace Panel 2","panelId":"DMP2","category":"ICT Services","jurisdiction":"Federal","deedStart":"01-Jul-2023","deedEnd":"30-Jun-2028","isActive":true}]},{"id":"63002915648","name":"Samsung Electronics Australia Pty Ltd","abn":"63002915648","buyictURL":"https://www.buyict.gov.au/public?id=seller_details&abn=63002915648","headquarters":"NSW2127","panels":[{"panelName":"Hardware Marketplace","panelId":"PNL1868","category":"Hardware","jurisdiction":"Federal","deedStart":"24-Sep-2018","deedEnd":"30-Jun-2026","isActive":true},{"panelName":"Digital Marketplace Panel 2","panelId":"DMP2","category":"ICT Services","jurisdiction":"Federal","deedStart":"01-Jul-2023","deedEnd":"30-Jun-2028","isActive":true}]},{"id":"56662169806","name":"Sans Prejudice Solutions","abn":"56662169806","buyictURL":"https://www.buyict.gov.au/public?id=seller_details&abn=56662169806","panels":[{"panelName":"Digital Marketplace Panel 2","panelId":"DMP2","category":"ICT Services","jurisdiction":"Federal","deedStart":"01-Jul-2023","deedEnd":"30-Jun-2028","isActive":true}]},{"id":"68650373826","name":"Sapian Consultancy","abn":"68650373826","buyictURL":"https://www.buyict.gov.au/public?id=seller_details&abn=68650373826","panels":[{"panelName":"Digital Marketplace Panel 2","panelId":"DMP2","category":"ICT Services","jurisdiction":"Federal","deedStart":"01-Jul-2023","deedEnd":"30-Jun-2028","isActive":true}]},{"id":"70624711397","name":"SARVASARAN","abn":"70624711397","buyictURL":"https://www.buyict.gov.au/public?id=seller_details&abn=70624711397","panels":[{"panelName":"Digital Marketplace Panel 2","panelId":"DMP2","category":"ICT Services","jurisdiction":"Federal","deedStart":"01-Jul-2023","deedEnd":"30-Jun-2028","isActive":true}]},{"id":"68603349631","name":"Satcom Direct - Australia PTY LTD","abn":"68603349631","buyictURL":"https://www.buyict.gov.au/public?id=seller_details&abn=68603349631","headquarters":"VIC3041","panels":[{"panelName":"Telecommunications Marketplace","panelId":"PNL2222","category":"Telecommunications","jurisdiction":"Federal","deedStart":"07-Sep-2020","deedEnd":"30-Jun-2027","isActive":true}]},{"id":"89632263917","name":"Sauce Consulting Pty Ltd","abn":"89632263917","buyictURL":"https://www.buyict.gov.au/public?id=seller_details&abn=89632263917","panels":[{"panelName":"Digital Marketplace Panel 2","panelId":"DMP2","category":"ICT Services","jurisdiction":"Federal","deedStart":"01-Jul-2023","deedEnd":"30-Jun-2028","isActive":true}]},{"id":"20128397464","name":"Screencraft Media","abn":"20128397464","buyictURL":"https://www.buyict.gov.au/public?id=seller_details&abn=20128397464","panels":[{"panelName":"Digital Marketplace Panel 2","panelId":"DMP2","category":"ICT Services","jurisdiction":"Federal","deedStart":"01-Jul-2023","deedEnd":"30-Jun-2028","isActive":true}]},{"id":"20607773291","name":"Scyne Advisory Pty Ltd","abn":"20607773291","buyictURL":"https://www.buyict.gov.au/public?id=seller_details&abn=20607773291","panels":[{"panelName":"Digital Marketplace Panel 2","panelId":"DMP2","category":"ICT Services","jurisdiction":"Federal","deedStart":"01-Jul-2023","deedEnd":"30-Jun-2028","isActive":true}]},{"id":"11118316957","name":"SDACS","abn":"11118316957","buyictURL":"https://www.buyict.gov.au/public?id=seller_details&abn=11118316957","panels":[{"panelName":"Digital Marketplace Panel 2","panelId":"DMP2","category":"ICT Services","jurisdiction":"Federal","deedStart":"01-Jul-2023","deedEnd":"30-Jun-2028","isActive":true}]},{"id":"43618625773","name":"Seamless Intelligence","abn":"43618625773","buyictURL":"https://www.buyict.gov.au/public?id=seller_details&abn=43618625773","panels":[{"panelName":"Digital Marketplace Panel 2","panelId":"DMP2","category":"ICT Services","jurisdiction":"Federal","deedStart":"01-Jul-2023","deedEnd":"30-Jun-2028","isActive":true}]},{"id":"62649382817","name":"Sectorlink","abn":"62649382817","buyictURL":"https://www.buyict.gov.au/public?id=seller_details&abn=62649382817","panels":[{"panelName":"Digital Marketplace Panel 2","panelId":"DMP2","category":"ICT Services","jurisdiction":"Federal","deedStart":"01-Jul-2023","deedEnd":"30-Jun-2028","isActive":true}]},{"id":"13146261529","name":"Secure Agility Pty Ltd","abn":"13146261529","buyictURL":"https://www.buyict.gov.au/public?id=seller_details&abn=13146261529","headquarters":"NSW2134","panels":[{"panelName":"Telecommunications Marketplace","panelId":"PNL2222","category":"Telecommunications","jurisdiction":"Federal","deedStart":"07-Sep-2020","deedEnd":"30-Jun-2027","isActive":true},{"panelName":"Hardware Marketplace","panelId":"PNL1868","category":"Hardware","jurisdiction":"Federal","deedStart":"24-Sep-2018","deedEnd":"30-Jun-2026","isActive":true},{"panelName":"Digital Marketplace Panel 2","panelId":"DMP2","category":"ICT Services","jurisdiction":"Federal","deedStart":"01-Jul-2023","deedEnd":"30-Jun-2028","isActive":true}]},{"id":"51117003657","name":"Secure Bits Pty. Ltd.","abn":"51117003657","buyictURL":"https://www.buyict.gov.au/public?id=seller_details&abn=51117003657","headquarters":"ACT2609","panels":[{"panelName":"Hardware Marketplace","panelId":"PNL1868","category":"Hardware","jurisdiction":"Federal","deedStart":"24-Sep-2018","deedEnd":"30-Jun-2026","isActive":true},{"panelName":"Digital Marketplace Panel 2","panelId":"DMP2","category":"ICT Services","jurisdiction":"Federal","deedStart":"01-Jul-2023","deedEnd":"30-Jun-2028","isActive":true}]},{"id":"69145533580","name":"Secure Collaboration Pty Ltd","abn":"69145533580","buyictURL":"https://www.buyict.gov.au/public?id=seller_details&abn=69145533580","panels":[{"panelName":"Digital Marketplace Panel 2","panelId":"DMP2","category":"ICT Services","jurisdiction":"Federal","deedStart":"01-Jul-2023","deedEnd":"30-Jun-2028","isActive":true}]},{"id":"11146473314","name":"SECURE HARD DRIVE DESTRUCTION PTY. LTD.","abn":"11146473314","buyictURL":"https://www.buyict.gov.au/public?id=seller_details&abn=11146473314","headquarters":"VIC3033","panels":[{"panelName":"Hardware Marketplace","panelId":"PNL1868","category":"Hardware","jurisdiction":"Federal","deedStart":"24-Sep-2018","deedEnd":"30-Jun-2026","isActive":true},{"panelName":"Digital Marketplace Panel 2","panelId":"DMP2","category":"ICT Services","jurisdiction":"Federal","deedStart":"01-Jul-2023","deedEnd":"30-Jun-2028","isActive":true}]},{"id":"61647788743","name":"Securing Enterprises","abn":"61647788743","buyictURL":"https://www.buyict.gov.au/public?id=seller_details&abn=61647788743","panels":[{"panelName":"Digital Marketplace Panel 2","panelId":"DMP2","category":"ICT Services","jurisdiction":"Federal","deedStart":"01-Jul-2023","deedEnd":"30-Jun-2028","isActive":true}]},{"id":"80145039961","name":"SecurIQ","abn":"80145039961","buyictURL":"https://www.buyict.gov.au/public?id=seller_details&abn=80145039961","panels":[{"panelName":"Digital Marketplace Panel 2","panelId":"DMP2","category":"ICT Services","jurisdiction":"Federal","deedStart":"01-Jul-2023","deedEnd":"30-Jun-2028","isActive":true}]},{"id":"91616303238","name":"Security Shift","abn":"91616303238","buyictURL":"https://www.buyict.gov.au/public?id=seller_details&abn=91616303238","panels":[{"panelName":"Digital Marketplace Panel 2","panelId":"DMP2","category":"ICT Services","jurisdiction":"Federal","deedStart":"01-Jul-2023","deedEnd":"30-Jun-2028","isActive":true}]},{"id":"22668639156","name":"See Me Please","abn":"22668639156","buyictURL":"https://www.buyict.gov.au/public?id=seller_details&abn=22668639156","panels":[{"panelName":"Digital Marketplace Panel 2","panelId":"DMP2","category":"ICT Services","jurisdiction":"Federal","deedStart":"01-Jul-2023","deedEnd":"30-Jun-2028","isActive":true}]},{"id":"77150521574","name":"See-out Pty Ltd","abn":"77150521574","buyictURL":"https://www.buyict.gov.au/public?id=seller_details&abn=77150521574","panels":[{"panelName":"Digital Marketplace Panel 2","panelId":"DMP2","category":"ICT Services","jurisdiction":"Federal","deedStart":"01-Jul-2023","deedEnd":"30-Jun-2028","isActive":true}]},{"id":"56616067899","name":"SEER DATA & ANALYTICS PTY LTD","abn":"56616067899","buyictURL":"https://www.buyict.gov.au/public?id=seller_details&abn=56616067899","panels":[{"panelName":"Digital Marketplace Panel 2","panelId":"DMP2","category":"ICT Services","jurisdiction":"Federal","deedStart":"01-Jul-2023","deedEnd":"30-Jun-2028","isActive":true}]},{"id":"20664129855","name":"SEKER PATROL PTY LTD","abn":"20664129855","buyictURL":"https://www.buyict.gov.au/public?id=seller_details&abn=20664129855","panels":[{"panelName":"Digital Marketplace Panel 2","panelId":"DMP2","category":"ICT Services","jurisdiction":"Federal","deedStart":"01-Jul-2023","deedEnd":"30-Jun-2028","isActive":true}]},{"id":"38606881996","name":"SEKURO OPERATIONS","abn":"38606881996","buyictURL":"https://www.buyict.gov.au/public?id=seller_details&abn=38606881996","panels":[{"panelName":"Digital Marketplace Panel 2","panelId":"DMP2","category":"ICT Services","jurisdiction":"Federal","deedStart":"01-Jul-2023","deedEnd":"30-Jun-2028","isActive":true}]},{"id":"48610782950","name":"SEMA TECHNOLOGIES","abn":"48610782950","buyictURL":"https://www.buyict.gov.au/public?id=seller_details&abn=48610782950","panels":[{"panelName":"Digital Marketplace Panel 2","panelId":"DMP2","category":"ICT Services","jurisdiction":"Federal","deedStart":"01-Jul-2023","deedEnd":"30-Jun-2028","isActive":true}]},{"id":"81663579324","name":"Semantic Consulting","abn":"81663579324","buyictURL":"https://www.buyict.gov.au/public?id=seller_details&abn=81663579324","panels":[{"panelName":"Digital Marketplace Panel 2","panelId":"DMP2","category":"ICT Services","jurisdiction":"Federal","deedStart":"01-Jul-2023","deedEnd":"30-Jun-2028","isActive":true}]},{"id":"87162736441","name":"Semaphore Consulting Partners","abn":"87162736441","buyictURL":"https://www.buyict.gov.au/public?id=seller_details&abn=87162736441","panels":[{"panelName":"Digital Marketplace Panel 2","panelId":"DMP2","category":"ICT Services","jurisdiction":"Federal","deedStart":"01-Jul-2023","deedEnd":"30-Jun-2028","isActive":true}]},{"id":"86729917461","name":"SENSE","abn":"86729917461","buyictURL":"https://www.buyict.gov.au/public?id=seller_details&abn=86729917461","panels":[{"panelName":"Digital Marketplace Panel 2","panelId":"DMP2","category":"ICT Services","jurisdiction":"Federal","deedStart":"01-Jul-2023","deedEnd":"30-Jun-2028","isActive":true}]},{"id":"34610828656","name":"Sensei Productivity Pty Ltd","abn":"34610828656","buyictURL":"https://www.buyict.gov.au/public?id=seller_details&abn=34610828656","panels":[{"panelName":"Digital Marketplace Panel 2","panelId":"DMP2","category":"ICT Services","jurisdiction":"Federal","deedStart":"01-Jul-2023","deedEnd":"30-Jun-2028","isActive":true}]},{"id":"77606694615","name":"Sentaris Pty Ltd","abn":"77606694615","buyictURL":"https://www.buyict.gov.au/public?id=seller_details&abn=77606694615","panels":[{"panelName":"Digital Marketplace Panel 2","panelId":"DMP2","category":"ICT Services","jurisdiction":"Federal","deedStart":"01-Jul-2023","deedEnd":"30-Jun-2028","isActive":true}]},{"id":"67641651524","name":"Seqcure","abn":"67641651524","buyictURL":"https://www.buyict.gov.au/public?id=seller_details&abn=67641651524","panels":[{"panelName":"Digital Marketplace Panel 2","panelId":"DMP2","category":"ICT Services","jurisdiction":"Federal","deedStart":"01-Jul-2023","deedEnd":"30-Jun-2028","isActive":true}]},{"id":"44100234179","name":"Seven Consulting","abn":"44100234179","buyictURL":"https://www.buyict.gov.au/public?id=seller_details&abn=44100234179","panels":[{"panelName":"Digital Marketplace Panel 2","panelId":"DMP2","category":"ICT Services","jurisdiction":"Federal","deedStart":"01-Jul-2023","deedEnd":"30-Jun-2028","isActive":true}]},{"id":"91662206322","name":"SHAH CYBER SECURITY SOLUTIONS PTY LTD","abn":"91662206322","buyictURL":"https://www.buyict.gov.au/public?id=seller_details&abn=91662206322","panels":[{"panelName":"Digital Marketplace Panel 2","panelId":"DMP2","category":"ICT Services","jurisdiction":"Federal","deedStart":"01-Jul-2023","deedEnd":"30-Jun-2028","isActive":true}]},{"id":"57634812865","name":"Shakewell Agency","abn":"57634812865","buyictURL":"https://www.buyict.gov.au/public?id=seller_details&abn=57634812865","panels":[{"panelName":"Digital Marketplace Panel 2","panelId":"DMP2","category":"ICT Services","jurisdiction":"Federal","deedStart":"01-Jul-2023","deedEnd":"30-Jun-2028","isActive":true}]},{"id":"60939579224","name":"Sharp & Carter","abn":"60939579224","buyictURL":"https://www.buyict.gov.au/public?id=seller_details&abn=60939579224","panels":[{"panelName":"Digital Marketplace Panel 2","panelId":"DMP2","category":"ICT Services","jurisdiction":"Federal","deedStart":"01-Jul-2023","deedEnd":"30-Jun-2028","isActive":true}]},{"id":"40003039405","name":"SHARP CORPORATION OF AUSTRALIA PTY LTD","abn":"40003039405","buyictURL":"https://www.buyict.gov.au/public?id=seller_details&abn=40003039405","headquarters":"NSW2113","panels":[{"panelName":"Hardware Marketplace","panelId":"PNL1868","category":"Hardware","jurisdiction":"Federal","deedStart":"08-Sep-2022","deedEnd":"30-Jun-2026","isActive":true},{"panelName":"Digital Marketplace Panel 2","panelId":"DMP2","category":"ICT Services","jurisdiction":"Federal","deedStart":"01-Jul-2023","deedEnd":"30-Jun-2028","isActive":true}]},{"id":"26635524220","name":"SHC International Pty Ltd","abn":"26635524220","buyictURL":"https://www.buyict.gov.au/public?id=seller_details&abn=26635524220","panels":[{"panelName":"Digital Marketplace Panel 2","panelId":"DMP2","category":"ICT Services","jurisdiction":"Federal","deedStart":"01-Jul-2023","deedEnd":"30-Jun-2028","isActive":true}]}]